port_env/__init__.py
port_env/__main__.py
port_env/command.py
port_env-0.0.3.data/scripts/port_env
port_env-0.0.3.dist-info/METADATA
port_env-0.0.3.dist-info/WHEEL
port_env-0.0.3.dist-info/top_level.txt
port_env-0.0.3.dist-info/RECORD
