Metadata-Version: 2.1
Name: port_env
Version: 0.0.3
Summary: Make environments portable
Home-page: https://github.com/Moist-Cat/port_env
Author: Moist-Cat
Author-email: moistanonpy@gmail.com
License: UNKNOWN
Platform: UNKNOWN
Classifier: Programming Language :: Python :: 3
Classifier: Operating System :: POSIX :: Linux
Classifier: License :: OSI Approved :: MIT License
Requires-Python: >=3
